autoklug/__init__.py
autoklug/api.py
autoklug/config_permissions.py
autoklug/env.py
autoklug/error_handling.py
autoklug/error_messages.py
autoklug/examples.py
autoklug/functions.py
autoklug/layers.py
autoklug/main.py
autoklug/monitoring.py
autoklug/run.py
autoklug/templates.py
autoklug/test_runner.py
autoklug/testing.py
autoklug/utils.py
autoklug/validation.py
autoklug/core/builders/__init__.py
autoklug/core/cli/__init__.py
autoklug/core/cli/build_commands.py
autoklug/core/cli/commands.py
autoklug/core/cli/deploy_commands.py
autoklug/core/cli/dev_commands.py
autoklug/core/cli/env_commands.py
autoklug/core/cli/layer_commands.py
autoklug/core/cli/monitor_commands.py
autoklug/core/cli/template_commands.py
autoklug/core/cli/test_commands.py
autoklug/core/utils/__init__.py
autoklug/core/utils/zipping.py
autoklug-2.0.5.dist-info/licenses/LICENSE
autoklug-2.0.5.dist-info/METADATA
autoklug-2.0.5.dist-info/WHEEL
autoklug-2.0.5.dist-info/entry_points.txt
autoklug-2.0.5.dist-info/top_level.txt
autoklug-2.0.5.dist-info/RECORD
