Metadata-Version: 2.4
Name: autoklug
Version: 2.0.5
Summary: Blazing Fast AWS Lambda Build System with Global Project Detection
Home-page: https://github.com/lewisklug/autoklug
Author: Luís Miguel Sousa
Author-email: Luís Miguel Sousa <luis@kluglabs.com>
Maintainer-email: Luís Miguel Sousa <luis@kluglabs.com>
License: MIT
Project-URL: Homepage, https://github.com/lewisklug/autoklug
Project-URL: Documentation, https://github.com/lewisklug/autoklug#readme
Project-URL: Repository, https://github.com/lewisklug/autoklug
Project-URL: Issues, https://github.com/lewisklug/autoklug/issues
Keywords: aws,lambda,serverless,build,deployment,api-gateway,infrastructure,devops,ci-cd
Classifier: Development Status :: 5 - Production/Stable
Classifier: Intended Audience :: Developers
Classifier: Topic :: Software Development :: Build Tools
Classifier: Topic :: Software Development :: Libraries :: Python Modules
Classifier: License :: OSI Approved :: MIT License
Classifier: Programming Language :: Python :: 3
Classifier: Programming Language :: Python :: 3.8
Classifier: Programming Language :: Python :: 3.9
Classifier: Programming Language :: Python :: 3.10
Classifier: Programming Language :: Python :: 3.11
Classifier: Programming Language :: Python :: 3.12
Classifier: Operating System :: OS Independent
Classifier: Environment :: Console
Requires-Python: >=3.8
License-File: LICENSE
Requires-Dist: click>=8.0.0
Requires-Dist: boto3>=1.26.0
Requires-Dist: python-dotenv>=0.19.0
Requires-Dist: termcolor>=1.1.0
Requires-Dist: GitPython>=3.1.0
Requires-Dist: flask>=2.0.0
Requires-Dist: flask-cors>=3.0.0
Requires-Dist: requests>=2.25.0
Provides-Extra: dev
Requires-Dist: pytest>=7.0.0; extra == "dev"
Requires-Dist: pytest-asyncio>=0.21.0; extra == "dev"
Requires-Dist: black>=22.0.0; extra == "dev"
Requires-Dist: flake8>=5.0.0; extra == "dev"
Requires-Dist: mypy>=1.0.0; extra == "dev"
Provides-Extra: docs
Requires-Dist: mkdocs>=1.4.0; extra == "docs"
Requires-Dist: mkdocs-material>=8.0.0; extra == "docs"
Dynamic: author
Dynamic: home-page
Dynamic: license-file
Dynamic: requires-python
